oas_mini/__init__.py
oas_mini/__main__.py
oas_mini/oas_mini.py
oas_mini/facade/__init__.py
oas_mini/facade/approve.py
oas_mini/facade/deny.py
oas_mini/facade/deprovision.py
oas_mini/facade/instances.py
oas_mini/facade/provision.py
oas_mini/services/__init__.py
oas_mini/services/config_service.py
oas_mini/services/oas_service.py
oas_mini/swagg/__init__.py
oas_mini/swagg/endpoint.py
oas_mini/swagg/exceptions.py
oas_mini/swagg/factory.py
oas_mini/swagg/flags.py
oas_mini/swagg/service.py
oas_mini/utils/__init__.py
oas_mini/utils/facade.py
oas_mini/utils/helper.py
tests/__init__.py
tests/unit/__init__.py
tests/unit/test_client.py
tests/unit/swagg/__init__.py
tests/unit/swagg/test_endpoint.py
tests/unit/swagg/test_exceptions.py
tests/unit/swagg/test_factory.py
tests/unit/swagg/test_flags.py
tests/unit/utils/__init__.py
tests/unit/utils/test_helper.py
oas_mini-1.0.5.dist-info/METADATA
oas_mini-1.0.5.dist-info/WHEEL
oas_mini-1.0.5.dist-info/entry_points.txt
oas_mini-1.0.5.dist-info/top_level.txt
oas_mini-1.0.5.dist-info/RECORD
